capybara_orm/__init__.py
capybara_orm/config.py
capybara_orm/constants.py
capybara_orm/py.typed
capybara_orm/schemas.py
capybara_orm/utils.py
capybara_orm/cognite_adapters/__init__.py
capybara_orm/cognite_adapters/filter_mapper.py
capybara_orm/cognite_adapters/optimizer.py
capybara_orm/cognite_adapters/query_mapper.py
capybara_orm/cognite_adapters/query_result_mapper.py
capybara_orm/cognite_adapters/sort_mapper.py
capybara_orm/cognite_adapters/utils.py
capybara_orm/cognite_adapters/view_mapper.py
capybara_orm/engines/__init__.py
capybara_orm/engines/async_engine.py
capybara_orm/engines/engine.py
capybara_orm/models/__init__.py
capybara_orm/models/base.py
capybara_orm/models/entities.py
capybara_orm/statements/__init__.py
capybara_orm/statements/expressions.py
capybara_orm-0.2.1.dist-info/METADATA
capybara_orm-0.2.1.dist-info/WHEEL
capybara_orm-0.2.1.dist-info/RECORD
