Metadata-Version: 2.4
Name: capybara-orm
Version: 0.2.1
Summary: Add your description here
Author-email: Lucas Alves <lucasrosaalves@gmail.com>
Classifier: Programming Language :: Python
Classifier: Programming Language :: Python :: 3
Classifier: Programming Language :: Python :: 3 :: Only
Classifier: Programming Language :: Python :: 3.11
Classifier: Programming Language :: Python :: 3.12
Classifier: Programming Language :: Python :: 3.13
Classifier: Topic :: Database
Classifier: Topic :: Database :: Database Engines/Servers
Classifier: Typing :: Typed
Requires-Python: >=3.11
Requires-Dist: anyio>=4.9.0
Requires-Dist: cognite-sdk>=7.75.0
Requires-Dist: pydantic>=2.11.4
